pload/__init__.py
pload/cli.py
pload/managers/__init__.py
pload/managers/color.py
pload/managers/dependency.py
pload/managers/platform.py
pload/managers/pyversion.py
pload/managers/venv.py
pload-0.3.0.data/scripts/pload.fish
pload-0.3.0.data/scripts/pload.ps1
pload-0.3.0.data/scripts/pload.sh
pload-0.3.0.data/scripts/pload.zsh
pload-0.3.0.dist-info/licenses/LICENSE
pload-0.3.0.dist-info/METADATA
pload-0.3.0.dist-info/WHEEL
pload-0.3.0.dist-info/entry_points.txt
pload-0.3.0.dist-info/top_level.txt
pload-0.3.0.dist-info/RECORD
